odoo_regex_set/__init__.py
odoo_regex_set/manifest.py
odoo_regex_set/task.py
odoo_regex_set-0.2.dist-info/LICENSE
odoo_regex_set-0.2.dist-info/METADATA
odoo_regex_set-0.2.dist-info/WHEEL
odoo_regex_set-0.2.dist-info/top_level.txt
odoo_regex_set-0.2.dist-info/RECORD
