Metadata-Version: 2.1
Name: odoo-regex-set
Version: 0.2
Summary: Set of regex that ease our life.
Home-page: https://github.com/numigi/numiregex
Author: numigi
Author-email: contact@numigi.com
License: MIT
Platform: UNKNOWN
Classifier: License :: OSI Approved :: MIT License
Classifier: Programming Language :: Python
Classifier: Programming Language :: Python :: 3
Classifier: Programming Language :: Python :: 3.5
Classifier: Programming Language :: Python :: Implementation :: CPython
